regpol/__init__.py
regpol/regpol.py
regpol-0.1.2.dist-info/LICENSE
regpol-0.1.2.dist-info/METADATA
regpol-0.1.2.dist-info/WHEEL
regpol-0.1.2.dist-info/entry_points.txt
regpol-0.1.2.dist-info/top_level.txt
regpol-0.1.2.dist-info/RECORD
