Metadata-Version: 2.1
Name: regpol
Version: 0.1.2
Summary: Read Windows Registry.pol files
Home-page: https://github.com/jtpereyda/regpol
Maintainer: Joshua Pereyda
Maintainer-email: joshua.t.pereyda@gmail.com
License: UNKNOWN
Platform: UNKNOWN
Classifier: Development Status :: 4 - Beta
Classifier: Environment :: Console
Classifier: Intended Audience :: Developers
Classifier: Intended Audience :: Science/Research
Classifier: License :: OSI Approved :: MIT License
Classifier: Natural Language :: English
Classifier: Operating System :: OS Independent
Classifier: Programming Language :: Python
Classifier: Programming Language :: Python :: 3
Classifier: Programming Language :: Python :: 3.7
Classifier: Programming Language :: Python :: 3.8
Classifier: Topic :: Security
Requires-Python: >=3.7
Requires-Dist: click
